LICENSE
MANIFEST.in
README.md
pyproject.toml
setup.py
patentpy/__init__.py
patentpy/acquire.py
patentpy/convert_txt.py
patentpy/convert_xml1.py
patentpy/convert_xml2.py
patentpy/utility.py
patentpy.egg-info/PKG-INFO
patentpy.egg-info/SOURCES.txt
patentpy.egg-info/dependency_links.txt
patentpy.egg-info/not-zip-safe
patentpy.egg-info/requires.txt
patentpy.egg-info/top_level.txt
src/convert_funcs.cpp
src/convert_funcs.hpp
src/wrapper.cpp