Metadata-Version: 2.1
Name: patentpy
Version: 0.1.3
Summary: A project taking USPTO bulk patent data and converting it to rectangular format
Home-page: https://github.com/JYProjs/patentpy
Author: James Yu, Raoul Wadhwa, Hayley Beltz, Milind Y. Desai, Jacob G. Scott, Peter Erdi
Author-email: jyu140@jhu.edu
License: MIT
Platform: UNKNOWN
Classifier: Programming Language :: Python :: 3
Classifier: Programming Language :: C++
Classifier: License :: OSI Approved :: MIT License
Classifier: Operating System :: OS Independent
Classifier: Intended Audience :: Science/Research
Classifier: Intended Audience :: Information Technology
Classifier: Intended Audience :: Legal Industry
Classifier: Natural Language :: English
Classifier: Topic :: Utilities
Classifier: Topic :: Text Processing :: General
Classifier: Topic :: Text Processing :: Markup :: XML
Requires-Python: >=3.5
License-File: LICENSE
